<?xml version="1.0" encoding="utf-8"?>
<wp:comment xmlns:wp="http://wordpress.org/export/1.2/">
  <wp:comment_id>2114</wp:comment_id>
  <wp:comment_author><![CDATA[wcy]]></wp:comment_author>
  <wp:comment_author_email>wcyeee@gmail.com</wp:comment_author_email>
  <wp:comment_author_url></wp:comment_author_url>
  <wp:comment_author_IP>24.99.87.168</wp:comment_author_IP>
  <wp:comment_date>2008-08-08 19:14:49</wp:comment_date>
  <wp:comment_date_gmt>2008-08-09 02:14:49</wp:comment_date_gmt>
  <wp:comment_content><![CDATA[I wasn't as outraged as you by that clip. But, to your question, it's because everyone knows just how much of a dick he really can be:

Postmodern John McCain: the presidential candidate some Arizonans know — and loathe
http://www.phoenixnewtimes.com/content/printVersion/848709

Seriously, he made a tasteless joke about Chelsea Clinton who was a teen at the time? Wow, a bunch of old men laughing over that. Dick. Definitely.

On a lighter note, it's only deserving to laugh at the old coot and his early onset moments:

http://www.youtube.com/watch?v=iWX5u69hmzY

]]></wp:comment_content>
  <wp:comment_approved>1</wp:comment_approved>
  <wp:comment_type></wp:comment_type>
  <wp:comment_parent>0</wp:comment_parent>
  <wp:comment_user_id>0</wp:comment_user_id>
</wp:comment>