<?xml version="1.0" encoding="utf-8"?>
<item>
  <title>When you're REALLY into Cheese</title>
  <link>http://devhawk.net/2003/12/19/when-youre-really-into-cheese/</link>
  <pubDate>Fri, 19 Dec 2003 12:25:03 +0000</pubDate>
  <dc:creator xmlns:dc="http://purl.org/dc/elements/1.1/">devhawk</dc:creator>
  <guid isPermaLink="false">http://e6de0496-b593-4657-acd8-d602523c3fc4</guid>
  <description></description>
  <content:encoded xmlns:content="http://purl.org/rss/1.0/modules/content/"><![CDATA[<p>And I mean you love cheese. As in you rate cheese and say things to co-workers like "this is one of my top 15 cheeses in the world". You've got to check out <a href="http://www.cheesesociety.org/">The American Cheese Society</a> and their <a href="http://www.cheesesociety.org/pdf/JudgingBrochure03.pdf">annual conference and award winners</a>. They judged over 600 cheeses in 70 categories such as "Fresh Unripened Hispanic and Portuguese Style" and "Sheep's Milk Washed Rind". 
</p><p>Too bad they didn't judge any <a href="http://www.minderella.com/words/cheeseshop.htm">Venezuelan Beaver Cheese</a>.</p>]]></content:encoded>
  <excerpt:encoded xmlns:excerpt="http://wordpress.org/export/1.2/excerpt/"><![CDATA[]]></excerpt:encoded>
  <wp:post_id xmlns:wp="http://wordpress.org/export/1.2/">257</wp:post_id>
  <wp:post_date xmlns:wp="http://wordpress.org/export/1.2/">2003-12-19 12:25:03</wp:post_date>
  <wp:post_date_gmt xmlns:wp="http://wordpress.org/export/1.2/">2003-12-19 12:25:03</wp:post_date_gmt>
  <wp:comment_status xmlns:wp="http://wordpress.org/export/1.2/">open</wp:comment_status>
  <wp:ping_status xmlns:wp="http://wordpress.org/export/1.2/">open</wp:ping_status>
  <wp:post_name xmlns:wp="http://wordpress.org/export/1.2/">when-youre-really-into-cheese</wp:post_name>
  <wp:status xmlns:wp="http://wordpress.org/export/1.2/">publish</wp:status>
  <wp:post_parent xmlns:wp="http://wordpress.org/export/1.2/">0</wp:post_parent>
  <wp:menu_order xmlns:wp="http://wordpress.org/export/1.2/">0</wp:menu_order>
  <wp:post_type xmlns:wp="http://wordpress.org/export/1.2/">post</wp:post_type>
  <wp:post_password xmlns:wp="http://wordpress.org/export/1.2/"></wp:post_password>
  <wp:is_sticky xmlns:wp="http://wordpress.org/export/1.2/">0</wp:is_sticky>
  <category domain="category" nicename="uncategorized"><![CDATA[Uncategorized]]></category>
  <wp:postmeta xmlns:wp="http://wordpress.org/export/1.2/">
    <wp:meta_key>dasblog_entryid</wp:meta_key>
    <wp:meta_value><![CDATA[e6de0496-b593-4657-acd8-d602523c3fc4]]></wp:meta_value>
  </wp:postmeta>
  <wp:postmeta xmlns:wp="http://wordpress.org/export/1.2/">
    <wp:meta_key>dasblog_compressedtitle</wp:meta_key>
    <wp:meta_value><![CDATA[When+Youre+REALLY+Into+Cheese]]></wp:meta_value>
  </wp:postmeta>
  <wp:postmeta xmlns:wp="http://wordpress.org/export/1.2/">
    <wp:meta_key>dasblog_compressedtitleunique</wp:meta_key>
    <wp:meta_value><![CDATA[2003/12/19/When+Youre+REALLY+Into+Cheese]]></wp:meta_value>
  </wp:postmeta>
</item>