{"status":"ok","post":{"id":221,"type":"post","slug":"wining-the-war","url":"http:\/\/devhawk.net\/2003\/11\/02\/wining-the-war\/","status":"publish","title":"Wining the &#8220;War&#8221;","title_plain":"Wining the &#8220;War&#8221;","content":"<p>Rumsfeld said &#8220;<a href=\"http:\/\/msnbc.com\/news\/965704.asp\">We will win this war<\/a>&#8221; on Meet the Press today. Funny, I thought we <a href=\"http:\/\/www.cnn.com\/SPECIALS\/2003\/iraq\/war.tracker\/05.01.index.html\"> already had<\/a>.<\/p>\n<p>I&#8217;ve been reading &#8220;<a href=\"http:\/\/al-franken.com\/book.html\">LIES: And the Lying Liars Who Tell Them\u2014A Fair and Balanced Look at the Right<\/a>&#8221; by <a href=\"http:\/\/al-franken.com\">Al Franken<\/a>. Very funny, except when you think about what the current administration has done to this country. Then, it&#8217;s depressing.<\/p>\n","excerpt":"<p>Rumsfeld said &#8220;We will win this war&#8221; on Meet the Press today. Funny, I thought we already had. I&#8217;ve been reading &#8220;LIES: And the Lying Liars Who Tell Them\u2014A Fair and Balanced Look at the Right&#8221; by Al Franken. Very funny, except when you think about what the current administration has done to this country. [&hellip;]<\/p>\n","date":"2003-11-02 17:22:53","modified":"2011-04-16 23:03:35","categories":[{"id":219,"slug":"politics","title":"Politics","description":"","parent":0,"post_count":41}],"tags":[],"author":{"id":1,"slug":"admin","name":"DevHawk","first_name":"Harry","last_name":"Pierson","nickname":"DevHawk","url":"","description":""},"comments":[],"attachments":[],"comment_count":0,"comment_status":"closed","custom_fields":{"dasblog_entryid":["c8897d74-8a5e-46bb-b2ec-a609337d5773"],"dasblog_compressedtitle":["Wining+The+War"],"dasblog_compressedtitleunique":["2003\/11\/03\/Wining+The+War"]}},"previous_url":"http:\/\/devhawk.net\/2003\/11\/01\/architecture-update-online\/","next_url":"http:\/\/devhawk.net\/2003\/11\/04\/saf-day-one\/"}