{"status":"ok","post":{"id":477,"type":"post","slug":"technical-issues-resolved","url":"http:\/\/devhawk.net\/2004\/11\/08\/technical-issues-resolved\/","status":"publish","title":"Technical Issues Resolved","title_plain":"Technical Issues Resolved","content":"<p>We&#8217;ve had some technical difficulties around here. <a href=\"http:\/\/conpro.net\/\">Tom<\/a> installed ASP.NET 2.0 Beta 1 on this box and it automatically upgraded all the web apps on the machine to the new version. It caused a bunch of issues including breaking the admin interface and requiring a reboot every few hours. I spent some time this afternoon getting all the web apps back on ASP.NET 1.1. I uninstalled all of the beta bits, but it still didn&#8217;t work &#8211; I needed to use the aspnet_regiis utility to completely uninstall the IIS registration and then reinstall. I get the feeling that I could have left the beta bits hanging installed and just used aspnet_regiis to reset the registration, but better safe than sorry.<\/p>\n<p>Anyway, since I couldn&#8217;t log in, I obviously couldn&#8217;t blog. I keep an Outlook task folder of &#8220;Shit to Blog&#8221; that&#8217;s gathered a few items, so I&#8217;m looking forward to getting those posted. <\/p>\n","excerpt":"<p>We&#8217;ve had some technical difficulties around here. Tom installed ASP.NET 2.0 Beta 1 on this box and it automatically upgraded all the web apps on the machine to the new version. It caused a bunch of issues including breaking the admin interface and requiring a reboot every few hours. I spent some time this afternoon [&hellip;]<\/p>\n","date":"2004-11-08 18:57:25","modified":"2004-11-08 18:57:25","categories":[],"tags":[{"id":184,"slug":"blogging","title":"Blogging","description":"","post_count":122}],"author":{"id":1,"slug":"admin","name":"DevHawk","first_name":"Harry","last_name":"Pierson","nickname":"DevHawk","url":"","description":""},"comments":[],"attachments":[],"comment_count":0,"comment_status":"closed","custom_fields":{"dasblog_entryid":["65e79817-f7b0-4a0a-9dba-884f048bce44"],"dasblog_compressedtitle":["Technical+Issues+Resolved"],"dasblog_compressedtitleunique":["2004\/11\/09\/Technical+Issues+Resolved"]}},"previous_url":"http:\/\/devhawk.net\/2004\/11\/08\/dsl-tools-now-available\/","next_url":"http:\/\/devhawk.net\/2004\/11\/08\/movie-times-on-your-spot-watch\/"}