<?xml version="1.0" encoding="utf-8"?>
<item>
  <title>Starting in on SQL Service Broker</title>
  <link>http://devhawk.net/2004/12/07/starting-in-on-sql-service-broker/</link>
  <pubDate>Tue, 07 Dec 2004 15:43:12 +0000</pubDate>
  <dc:creator xmlns:dc="http://purl.org/dc/elements/1.1/">devhawk</dc:creator>
  <guid isPermaLink="false">http://57beeec2-ee56-4510-9232-9bde67f945da</guid>
  <description></description>
  <content:encoded xmlns:content="http://purl.org/rss/1.0/modules/content/"><![CDATA[<p>Since <a href="http://atlasbrandview.blogspot.com/">Norman</a> joined the team a few months ago, I’m no longer in firefighter mode. For about six months my team was short a marketing manager and I ended up picking up a bunch of extra duties. For example, I took over as TechEd architect track owner when out previous marketing manager left. I don’t know much about marketing, but I guess I did OK – I received a Marketing Impact Award for my work on TechEd. However, I’m very happy to have handed those marketing responsibilities back to their rightful owner. Even still, Norman is trying to educate me about marketing. He made me read the first two chapters of <a href="http://www.amazon.com/o/ASIN/002900151X">Building Strong Brands</a> by David Aaker. I actually got thru the first three chapters before borrowing <a href="http://www.amazon.com/o/ASIN/1576750744">Birth of the Chaordic Age</a> by Dee Hock from my father at Thanksgiving. </p><p>You would think that I would now have more time for blogging, but alas that has not been the case. When I was firefighting, I had no time for planning. Now, of course, I do. So between planning and thanksgiving vacation I’ve just been too busy to blog much.</p><p>One thing I’m getting into recently is SQL Service Broker. I’m working on an interesting community project that is building on top of SSB. Luckily, one of the <a href="http://blogs.msdn.com/pathelland">primary architects</a> of SSB sits down the hall from me. Of course, not everyone is so lucky, so watch this space as I dig deeper on SSB. A good place to start is the <a href="http://msdn.com/library/en-us/dnsql90/html/sqlsvcbroker.asp">SSB First Look</a> article. In order to start getting a handle on SSB, I ported the Hello World example from that article from T-SQL to C#. It’s a bit tricky, as there is no SSB-specific framework – you just use SqlCommand to execute SSB commands like BEGIN DIALOG and RECEIVE – but otherwise it’s pretty straightforward. My sample also demonstrates using the new SQL Management Objects to create databases and SSB related objects (message types, contracts, queues and services). <a href="http://cid-0d9bc809858885a4.office.live.com/self.aspx/DevHawk%20Content/BlogFiles/HelloSSB.zip">Here’s the code</a> – enjoy.</p>]]></content:encoded>
  <excerpt:encoded xmlns:excerpt="http://wordpress.org/export/1.2/excerpt/"><![CDATA[]]></excerpt:encoded>
  <wp:post_id xmlns:wp="http://wordpress.org/export/1.2/">490</wp:post_id>
  <wp:post_date xmlns:wp="http://wordpress.org/export/1.2/">2004-12-07 15:43:12</wp:post_date>
  <wp:post_date_gmt xmlns:wp="http://wordpress.org/export/1.2/">2004-12-07 15:43:12</wp:post_date_gmt>
  <wp:comment_status xmlns:wp="http://wordpress.org/export/1.2/">open</wp:comment_status>
  <wp:ping_status xmlns:wp="http://wordpress.org/export/1.2/">open</wp:ping_status>
  <wp:post_name xmlns:wp="http://wordpress.org/export/1.2/">starting-in-on-sql-service-broker</wp:post_name>
  <wp:status xmlns:wp="http://wordpress.org/export/1.2/">publish</wp:status>
  <wp:post_parent xmlns:wp="http://wordpress.org/export/1.2/">0</wp:post_parent>
  <wp:menu_order xmlns:wp="http://wordpress.org/export/1.2/">0</wp:menu_order>
  <wp:post_type xmlns:wp="http://wordpress.org/export/1.2/">post</wp:post_type>
  <wp:post_password xmlns:wp="http://wordpress.org/export/1.2/"></wp:post_password>
  <wp:is_sticky xmlns:wp="http://wordpress.org/export/1.2/">0</wp:is_sticky>
  <category domain="category" nicename="architecture"><![CDATA[Architecture]]></category>
  <category domain="post_tag" nicename="soa"><![CDATA[SOA]]></category>
  <wp:postmeta xmlns:wp="http://wordpress.org/export/1.2/">
    <wp:meta_key>dasblog_entryid</wp:meta_key>
    <wp:meta_value><![CDATA[57beeec2-ee56-4510-9232-9bde67f945da]]></wp:meta_value>
  </wp:postmeta>
  <wp:postmeta xmlns:wp="http://wordpress.org/export/1.2/">
    <wp:meta_key>dasblog_compressedtitle</wp:meta_key>
    <wp:meta_value><![CDATA[Starting+In+On+SQL+Service+Broker]]></wp:meta_value>
  </wp:postmeta>
  <wp:postmeta xmlns:wp="http://wordpress.org/export/1.2/">
    <wp:meta_key>dasblog_compressedtitleunique</wp:meta_key>
    <wp:meta_value><![CDATA[2004/12/07/Starting+In+On+SQL+Service+Broker]]></wp:meta_value>
  </wp:postmeta>
  <wp:comment xmlns:wp="http://wordpress.org/export/1.2/">
    <wp:comment_id>2730</wp:comment_id>
    <wp:comment_author><![CDATA[言情小说]]></wp:comment_author>
    <wp:comment_author_email>icebluewxl@163.com</wp:comment_author_email>
    <wp:comment_author_url>http://www.readnovel.com/ch/2.html</wp:comment_author_url>
    <wp:comment_author_IP></wp:comment_author_IP>
    <wp:comment_date>2004-12-14 21:09:49</wp:comment_date>
    <wp:comment_date_gmt>2004-12-15 05:09:49</wp:comment_date_gmt>
    <wp:comment_content><![CDATA[Too pity! I can’t help crying for you.]]></wp:comment_content>
    <wp:comment_approved>1</wp:comment_approved>
    <wp:comment_type></wp:comment_type>
    <wp:comment_parent>0</wp:comment_parent>
    <wp:comment_user_id>0</wp:comment_user_id>
  </wp:comment>
  <wp:comment xmlns:wp="http://wordpress.org/export/1.2/">
    <wp:comment_id>2731</wp:comment_id>
    <wp:comment_author><![CDATA[言情小说]]></wp:comment_author>
    <wp:comment_author_email>icebluewxl@163.com</wp:comment_author_email>
    <wp:comment_author_url>http://www.readnovel.com/ch/2.html</wp:comment_author_url>
    <wp:comment_author_IP></wp:comment_author_IP>
    <wp:comment_date>2004-12-14 21:13:13</wp:comment_date>
    <wp:comment_date_gmt>2004-12-15 05:13:13</wp:comment_date_gmt>
    <wp:comment_content><![CDATA[Too pity! I can’t help crying for you.]]></wp:comment_content>
    <wp:comment_approved>1</wp:comment_approved>
    <wp:comment_type></wp:comment_type>
    <wp:comment_parent>0</wp:comment_parent>
    <wp:comment_user_id>0</wp:comment_user_id>
  </wp:comment>
</item>