<?xml version="1.0" encoding="utf-8"?>
<wp:comment xmlns:wp="http://wordpress.org/export/1.2/">
  <wp:comment_id>2353</wp:comment_id>
  <wp:comment_author><![CDATA[Dan McKinley]]></wp:comment_author>
  <wp:comment_author_email></wp:comment_author_email>
  <wp:comment_author_url>http://mcfunley.com</wp:comment_author_url>
  <wp:comment_author_IP>198.45.18.20</wp:comment_author_IP>
  <wp:comment_date>2006-04-25 10:48:58</wp:comment_date>
  <wp:comment_date_gmt>2006-04-25 17:48:58</wp:comment_date_gmt>
  <wp:comment_content><![CDATA[Good post. I think this concept intersects with the phenomenon of "cargo cult" programming to some degree. On my team, the old timers are in the habit of setting local references to Nothing when using VB.NET. Ie,

Public Sub Foo()
  Dim x As New Object
  ' Use x
  x = Nothing
End Sub

Nobody can explain how this got started and I've had some extreme difficulty explaining this is not necessary.]]></wp:comment_content>
  <wp:comment_approved>1</wp:comment_approved>
  <wp:comment_type></wp:comment_type>
  <wp:comment_parent>0</wp:comment_parent>
  <wp:comment_user_id>0</wp:comment_user_id>
</wp:comment>