{
  "slug": "joining-windows",
  "title": "Joining Windows",
  "date": "2009-10-26T17:22:43-07:00",
  "modified": "2011-04-17T07:28:14-07:00",
  "csv-category-slugs": "Windows|windows",
  "csv-tag-slugs": "Working at MSFT|working-at-msft",
  "author": "DevHawk|devhawk|harry@devhawk.net",
  "comment-count": 4,
  "dasblog-entry-id": "16570446-12d5-47c1-be94-5a8d1754110a",
  "dasblog-title": "Joining+Windows",
  "dasblog-unique-title": "2009/10/27/Joining+Windows",
  "sha1": "08e01cbee3e7aba5d244a8589df45b8c0a68b3b9"
}