{"status":"ok","post":{"id":202,"type":"post","slug":"2-great-technologies-that-taste-great-together","url":"http:\/\/devhawk.net\/2003\/10\/06\/2-great-technologies-that-taste-great-together\/","status":"publish","title":"2 Great Technologies that Taste Great Together","title_plain":"2 Great Technologies that Taste Great Together","content":"<p>If you like C++ and CLI, you&#8217;re going to love <a href=\"http:\/\/www.ecma-international.org\">ECMA<\/a> TG5 of TC39. Task Group 5 of Technical Committee 39 is going to tackle <a href=\"http:\/\/www.ecma-international.org\/news\/ecma-TG5-PR.htm\">C++ bindings for CLI<\/a>. Since it&#8217;s starting from a draft to be submitted by Microsoft, I assume they will be using all the existing keywords like __gc, __value and __property. I wonder if they&#8217;ll strip out the double underscore prefix?<\/p>\n<p>BTW, if you think the C++ \/ CLI combination is a waste of time, I say don&#8217;t knock it &#8217;till you try it. If you&#8217;re wrapping an existing codebase with a C or C++ API, it&#8217;s much easier to expose a managed interface with MC++ than C#. Don&#8217;t believe me? Go take a complicated C structure like <a href=\"http:\/\/msdn.microsoft.com\/library\/en-us\/winsock\/winsock\/wsaqueryset_2.asp\"> WSAQUERYSET<\/a> and implement it via C#.<\/p>\n","excerpt":"<p>If you like C++ and CLI, you&#8217;re going to love ECMA TG5 of TC39. Task Group 5 of Technical Committee 39 is going to tackle C++ bindings for CLI. Since it&#8217;s starting from a draft to be submitted by Microsoft, I assume they will be using all the existing keywords like __gc, __value and __property. [&hellip;]<\/p>\n","date":"2003-10-06 21:18:53","modified":"2003-10-06 21:18:53","categories":[],"tags":[],"author":{"id":1,"slug":"admin","name":"DevHawk","first_name":"Harry","last_name":"Pierson","nickname":"DevHawk","url":"","description":""},"comments":[],"attachments":[],"comment_count":0,"comment_status":"closed","custom_fields":{"dasblog_entryid":["a6428efe-595e-479a-a3df-3897d6679977"],"dasblog_compressedtitle":["2+Great+Technologies+That+Taste+Great+Together"],"dasblog_compressedtitleunique":["2003\/10\/07\/2+Great+Technologies+That+Taste+Great+Together"]}},"previous_url":"http:\/\/devhawk.net\/2003\/10\/05\/back-in-blog\/","next_url":"http:\/\/devhawk.net\/2003\/10\/13\/reading-writing-and-business-cards\/"}