<?xml version="1.0" encoding="utf-8"?>
<wp:comment xmlns:wp="http://wordpress.org/export/1.2/">
  <wp:comment_id>2454</wp:comment_id>
  <wp:comment_author><![CDATA[Tomas Restrepo]]></wp:comment_author>
  <wp:comment_author_email>tomas@winterdom.com</wp:comment_author_email>
  <wp:comment_author_url>http://www.winterdom.com/weblog</wp:comment_author_url>
  <wp:comment_author_IP>200.116.233.120</wp:comment_author_IP>
  <wp:comment_date>2007-02-08 14:28:57</wp:comment_date>
  <wp:comment_date_gmt>2007-02-08 22:28:57</wp:comment_date_gmt>
  <wp:comment_content><![CDATA[Regarding the Colorized code in feeds, I'd like to know to. Several people seem to be able to do it without problems, but even though I've repeatedly asked about it (directly and indirectly) I have yet to hear an answer. Must be an important secret to guard it so closely.]]></wp:comment_content>
  <wp:comment_approved>1</wp:comment_approved>
  <wp:comment_type></wp:comment_type>
  <wp:comment_parent>0</wp:comment_parent>
  <wp:comment_user_id>0</wp:comment_user_id>
</wp:comment>