{"status":"ok","post":{"id":478,"type":"post","slug":"konfabulator","url":"http:\/\/devhawk.net\/2004\/11\/09\/konfabulator\/","status":"publish","title":"Konfabulator","title_plain":"Konfabulator","content":"<p>I just installed <a href=\"http:\/\/www.konfabulator.com\/\">Konfabulator<\/a> as I&#8217;ve seen several people,\u00a0like <a href=\"http:\/\/radio.weblogs.com\/0001011\/2004\/11\/08.html#a8588\">Scoble<\/a>, blogging about it. I think I need to dig thru the widget gallery. Of the preinstalled ones, I only like the Battery Level and WiFi Signal widgets. But I <em>really <\/em>like them &#8211; as in like them enough to keep the software installed just for them. I&#8217;ve only played with it for 5 minutes, but already I am not interested in any of the interactive widgits &#8211; having a nice partially transparent graphic displaying information at\u00a0a glance works for me the best. <\/p>\n<p>Esp. after the launch of Halo 2, I&#8217;d love to see a Konfabulator widget with the status of my Xbox Live Friends list. Maybe something for the <a href=\"http:\/\/www.xboxfriends.com\/\">XboxFriends<\/a> folks?<\/p>\n<p>Speaking of Halo 2, I&#8217;m headed home now to do just that&#8230;<\/p>\n","excerpt":"<p>I just installed Konfabulator as I&#8217;ve seen several people,\u00a0like Scoble, blogging about it. I think I need to dig thru the widget gallery. Of the preinstalled ones, I only like the Battery Level and WiFi Signal widgets. But I really like them &#8211; as in like them enough to keep the software installed just for [&hellip;]<\/p>\n","date":"2004-11-09 17:09:32","modified":"2004-11-09 17:09:32","categories":[{"id":223,"slug":"general-geekery","title":"General Geekery","description":"","parent":0,"post_count":35}],"tags":[],"author":{"id":1,"slug":"admin","name":"DevHawk","first_name":"Harry","last_name":"Pierson","nickname":"DevHawk","url":"","description":""},"comments":[],"attachments":[],"comment_count":0,"comment_status":"closed","custom_fields":{"dasblog_entryid":["e7126739-bb94-4440-aa34-18e0c7691b04"],"dasblog_compressedtitle":["Konfabulator"],"dasblog_compressedtitleunique":["2004\/11\/10\/Konfabulator"]}},"previous_url":"http:\/\/devhawk.net\/2004\/11\/09\/roger-sessions-on-ws\/","next_url":"http:\/\/devhawk.net\/2004\/11\/10\/halo-2-stats\/"}