{
  "slug": "wizmo-msn-deskbar",
  "title": "Wizmo + MSN Deskbar",
  "date": "2005-01-21T19:18:18-08:00",
  "modified": "2005-01-21T19:18:18-08:00",
  "csv-category-slugs": "General Geekery|general-geekery",
  "csv-tag-slugs": "",
  "author": "DevHawk|devhawk|harry@devhawk.net",
  "comment-count": 0,
  "dasblog-entry-id": "f758b505-6c9d-4111-a27e-e27cb64ac9eb",
  "dasblog-title": "Wizmo+MSN+Deskbar",
  "dasblog-unique-title": "2005/01/22/Wizmo+MSN+Deskbar",
  "sha1": "1b56594cda7b2dfd3fc1f195feac594a6baabf0e"
}