{
  "slug": "hanging-in-hobbiton",
  "title": "Hanging in Hobbiton",
  "date": "2004-08-01T16:54:46-07:00",
  "modified": "2004-08-01T16:54:46-07:00",
  "csv-category-slugs": "",
  "csv-tag-slugs": "",
  "author": "DevHawk|devhawk|harry@devhawk.net",
  "comment-count": 1,
  "dasblog-entry-id": "4b15f35b-ce4b-4708-9be4-2756dec73254",
  "dasblog-title": "Hanging+In+Hobbiton",
  "dasblog-unique-title": "2004/08/01/Hanging+In+Hobbiton",
  "sha1": "36501d3495b9db51d3e21a9fdf724261d26e8661"
}