<?xml version="1.0" encoding="utf-8"?>
<wp:comment xmlns:wp="http://wordpress.org/export/1.2/">
  <wp:comment_id>2275</wp:comment_id>
  <wp:comment_author><![CDATA[Martin Meinhardt]]></wp:comment_author>
  <wp:comment_author_email>am_tomoni@yahoo.de</wp:comment_author_email>
  <wp:comment_author_url></wp:comment_author_url>
  <wp:comment_author_IP>78.49.190.47</wp:comment_author_IP>
  <wp:comment_date>2009-09-29 06:43:03</wp:comment_date>
  <wp:comment_date_gmt>2009-09-29 13:43:03</wp:comment_date_gmt>
  <wp:comment_content><![CDATA["IronPython 2.6 D4"

"D" for "Dynamic" and "4" stands for ".NET v4".]]></wp:comment_content>
  <wp:comment_approved>1</wp:comment_approved>
  <wp:comment_type></wp:comment_type>
  <wp:comment_parent>0</wp:comment_parent>
  <wp:comment_user_id>0</wp:comment_user_id>
</wp:comment>