<?xml version="1.0" encoding="utf-8"?>
<item>
  <title>Props to MSN9</title>
  <link>http://devhawk.net/2004/01/09/props-to-msn9/</link>
  <pubDate>Fri, 09 Jan 2004 16:51:31 +0000</pubDate>
  <dc:creator xmlns:dc="http://purl.org/dc/elements/1.1/">devhawk</dc:creator>
  <guid isPermaLink="false">http://1b5b8342-b12f-4d8a-97f9-76868ad5afaa</guid>
  <description></description>
  <content:encoded xmlns:content="http://purl.org/rss/1.0/modules/content/"><![CDATA[<p>A bunch of people have already blogged the new <a href="http://www.msn.com/">MSN</a>. I mean, it did launch yesterday. (I feel so behind the times).</p><p>However, I have to blog on my favorite new feature - <a href="http://join.msn.com/?pgmarket=en-us&amp;page=features/richmail">integrated POP3 email</a>. I started using <a href="http://mozilla.org/products/thunderbird/">Thunderbird</a> because I wanted to keep my <a href="mailto:harry@devhawk.net">DevHawk email</a> seperate from my <a href="mailto:hpierson@microsoft.com">work</a> and personal email addresses. I used to use <a href="http://www.microsoft.com/windows/oe/">Outlook Express</a> but the lack of junk mail filtering doomed that choice (I know about tools like <a href="http://popfile.sourceforge.net/">POPFile</a>, but I wanted a single app solution). I also tried <a href="http://office.microsoft.com/home/office.aspx?assetid=FX01085793">Outlook 2003</a> which had good junk mail filtering but it was bad at keeping my email accounts seperate. The <a href="http://join.msn.com/?pgmarket=en-us&amp;page=byoa/plus">MSN Plus</a> and <a href="http://join.msn.com/?pgmarket=en-us&amp;page=byoa/prem">MSN Premium</a> both support accessing POP3 email address, keep the email seperate from my personal hotmail email and do a great job filtering junk. Cool!</p>]]></content:encoded>
  <excerpt:encoded xmlns:excerpt="http://wordpress.org/export/1.2/excerpt/"><![CDATA[]]></excerpt:encoded>
  <wp:post_id xmlns:wp="http://wordpress.org/export/1.2/">274</wp:post_id>
  <wp:post_date xmlns:wp="http://wordpress.org/export/1.2/">2004-01-09 16:51:31</wp:post_date>
  <wp:post_date_gmt xmlns:wp="http://wordpress.org/export/1.2/">2004-01-09 16:51:31</wp:post_date_gmt>
  <wp:comment_status xmlns:wp="http://wordpress.org/export/1.2/">open</wp:comment_status>
  <wp:ping_status xmlns:wp="http://wordpress.org/export/1.2/">open</wp:ping_status>
  <wp:post_name xmlns:wp="http://wordpress.org/export/1.2/">props-to-msn9</wp:post_name>
  <wp:status xmlns:wp="http://wordpress.org/export/1.2/">publish</wp:status>
  <wp:post_parent xmlns:wp="http://wordpress.org/export/1.2/">0</wp:post_parent>
  <wp:menu_order xmlns:wp="http://wordpress.org/export/1.2/">0</wp:menu_order>
  <wp:post_type xmlns:wp="http://wordpress.org/export/1.2/">post</wp:post_type>
  <wp:post_password xmlns:wp="http://wordpress.org/export/1.2/"></wp:post_password>
  <wp:is_sticky xmlns:wp="http://wordpress.org/export/1.2/">0</wp:is_sticky>
  <category domain="category" nicename="uncategorized"><![CDATA[Uncategorized]]></category>
  <wp:postmeta xmlns:wp="http://wordpress.org/export/1.2/">
    <wp:meta_key>dasblog_entryid</wp:meta_key>
    <wp:meta_value><![CDATA[1b5b8342-b12f-4d8a-97f9-76868ad5afaa]]></wp:meta_value>
  </wp:postmeta>
  <wp:postmeta xmlns:wp="http://wordpress.org/export/1.2/">
    <wp:meta_key>dasblog_compressedtitle</wp:meta_key>
    <wp:meta_value><![CDATA[Props+To+MSN9]]></wp:meta_value>
  </wp:postmeta>
  <wp:postmeta xmlns:wp="http://wordpress.org/export/1.2/">
    <wp:meta_key>dasblog_compressedtitleunique</wp:meta_key>
    <wp:meta_value><![CDATA[2004/01/10/Props+To+MSN9]]></wp:meta_value>
  </wp:postmeta>
  <wp:comment xmlns:wp="http://wordpress.org/export/1.2/">
    <wp:comment_id>2948</wp:comment_id>
    <wp:comment_author><![CDATA[Matt Berther]]></wp:comment_author>
    <wp:comment_author_email>matt@mattberther.com</wp:comment_author_email>
    <wp:comment_author_url>http://www.mattberther.com</wp:comment_author_url>
    <wp:comment_author_IP></wp:comment_author_IP>
    <wp:comment_date>2004-01-09 20:52:04</wp:comment_date>
    <wp:comment_date_gmt>2004-01-10 04:52:04</wp:comment_date_gmt>
    <wp:comment_content><![CDATA[So, pardon my ignorance...

Is there a way to get integrated POP3 email from MSN9 on a computer that doesnt have MSN9 on it?

ie: can I go to some website and check email when Im away from this computer and get it all in one spot?]]></wp:comment_content>
    <wp:comment_approved>1</wp:comment_approved>
    <wp:comment_type></wp:comment_type>
    <wp:comment_parent>0</wp:comment_parent>
    <wp:comment_user_id>0</wp:comment_user_id>
  </wp:comment>
  <wp:comment xmlns:wp="http://wordpress.org/export/1.2/">
    <wp:comment_id>2949</wp:comment_id>
    <wp:comment_author><![CDATA[Harry]]></wp:comment_author>
    <wp:comment_author_email></wp:comment_author_email>
    <wp:comment_author_url></wp:comment_author_url>
    <wp:comment_author_IP></wp:comment_author_IP>
    <wp:comment_date>2004-01-10 22:54:29</wp:comment_date>
    <wp:comment_date_gmt>2004-01-11 06:54:29</wp:comment_date_gmt>
    <wp:comment_content><![CDATA[As far as I understand (i.e. I'm not on the MSN team, so I'm not the expert), the POP3 support is a feature of the MSN client.]]></wp:comment_content>
    <wp:comment_approved>1</wp:comment_approved>
    <wp:comment_type></wp:comment_type>
    <wp:comment_parent>0</wp:comment_parent>
    <wp:comment_user_id>0</wp:comment_user_id>
  </wp:comment>
</item>