<?xml version="1.0" encoding="utf-8"?>
<wp:comment xmlns:wp="http://wordpress.org/export/1.2/">
  <wp:comment_id>3176</wp:comment_id>
  <wp:comment_author><![CDATA[DevHawk]]></wp:comment_author>
  <wp:comment_author_email>harry@devhawk.net</wp:comment_author_email>
  <wp:comment_author_url></wp:comment_author_url>
  <wp:comment_author_IP>131.107.0.102</wp:comment_author_IP>
  <wp:comment_date>2011-05-24 09:39:51</wp:comment_date>
  <wp:comment_date_gmt>2011-05-24 16:39:51</wp:comment_date_gmt>
  <wp:comment_content><![CDATA[@gautam, The code in this post is C#. There is a managed version of C++ (aka <a href="http://en.wikipedia.org/wiki/C%2B%2B/CLI" rel="nofollow">C++/CLI</a>) but I don't think it works with ASP.NET.]]></wp:comment_content>
  <wp:comment_approved>1</wp:comment_approved>
  <wp:comment_type></wp:comment_type>
  <wp:comment_parent>3175</wp:comment_parent>
  <wp:comment_user_id>1</wp:comment_user_id>
</wp:comment>