{"status":"ok","post":{"id":114,"type":"post","slug":"recognizable-identity","url":"http:\/\/devhawk.net\/2003\/06\/04\/recognizable-identity\/","status":"publish","title":"Recognizable Identity","title_plain":"Recognizable Identity","content":"<p>After introducing myself at a customer meeting today in Phoenix, someone asked &#8220;Are you the Harry Pierson from DevHawk?&#8221;. First time that&#8217;s happened &#8211; kinda cool. Nice that he recognized my real name &#8211; I think most people who read this blog just know me as &#8220;DevHawk&#8221;. A couple of times, I&#8217;ve introduced myself to blank stares then mention that I write DevHawk to instant recognititon. <\/p>\n<p>BTW, I did take the <a href=\"http:\/\/www.gotdotnet.com\/team\/mgudgin\/default.aspx\">plunge<\/a> and put the URL for my blog on my business cards.<\/p>\n","excerpt":"<p>After introducing myself at a customer meeting today in Phoenix, someone asked &#8220;Are you the Harry Pierson from DevHawk?&#8221;. First time that&#8217;s happened &#8211; kinda cool. Nice that he recognized my real name &#8211; I think most people who read this blog just know me as &#8220;DevHawk&#8221;. A couple of times, I&#8217;ve introduced myself to [&hellip;]<\/p>\n","date":"2003-06-04 20:54:43","modified":"2003-06-04 20:54:43","categories":[],"tags":[],"author":{"id":1,"slug":"admin","name":"DevHawk","first_name":"Harry","last_name":"Pierson","nickname":"DevHawk","url":"","description":""},"comments":[],"attachments":[],"comment_count":0,"comment_status":"closed","custom_fields":{"dasblog_entryid":["a3412320-89b6-46b9-bdd7-c1556c86c617"],"dasblog_compressedtitle":["Recognizable+Identity"],"dasblog_compressedtitleunique":["2003\/06\/05\/Recognizable+Identity"]}},"previous_url":"http:\/\/devhawk.net\/2003\/06\/04\/don-on-xml-apis\/","next_url":"http:\/\/devhawk.net\/2003\/06\/04\/blogging-on-the-tablet\/"}