{"status":"ok","post":{"id":481,"type":"post","slug":"more-architect-bloggers-2","url":"http:\/\/devhawk.net\/2004\/11\/11\/more-architect-bloggers-2\/","status":"publish","title":"More Architect Bloggers","title_plain":"More Architect Bloggers","content":"<p>Two new architect bloggers to report. <a href=\"http:\/\/blogs.msdn.com\/javeds\">Javed Sikander<\/a> is an architect on the Architecture Strategy Team focusing on RFID. He links to a <a href=\"http:\/\/www.microsoft.com\/presspass\/press\/2004\/apr04\/04-05MicrosoftRFIDPR.asp\">pair<\/a> of <a href=\"http:\/\/www.microsoft.com\/presspass\/features\/2003\/jun03\/06-11rfid.asp\">articles<\/a> about Microsoft and RFID plus provides <a href=\"http:\/\/blogs.msdn.com\/javeds\/archive\/2004\/11\/10\/255393.aspx\">his thoughts<\/a> on why RFID is a big deal. <a href=\"http:\/\/weblogs.asp.net\/beaudreaux\">David Solivan<\/a> is an architect advisor and an ex-teammate from my old .NET Adoption Team days. So far, David appears to be blogging at conferences. He started in July at MGB and then went dark for a few months. He picked back up at SAF. I hear he&#8217;s at a conference this week, so maybe we&#8217;ll see some more from him.<\/p>\n<p>That brings the total number of bloggers from my team to 14. That&#8217;s over half of the team and I know at least two more coming down the pipe.<\/p>\n","excerpt":"<p>Two new architect bloggers to report. Javed Sikander is an architect on the Architecture Strategy Team focusing on RFID. He links to a pair of articles about Microsoft and RFID plus provides his thoughts on why RFID is a big deal. David Solivan is an architect advisor and an ex-teammate from my old .NET Adoption [&hellip;]<\/p>\n","date":"2004-11-11 11:19:39","modified":"2004-11-11 11:19:39","categories":[{"id":177,"slug":"architecture","title":"Architecture","description":"","parent":0,"post_count":296}],"tags":[{"id":184,"slug":"blogging","title":"Blogging","description":"","post_count":122}],"author":{"id":1,"slug":"admin","name":"DevHawk","first_name":"Harry","last_name":"Pierson","nickname":"DevHawk","url":"","description":""},"comments":[],"attachments":[],"comment_count":0,"comment_status":"closed","custom_fields":{"dasblog_entryid":["df54a790-7131-493c-a06a-f5cac25b75cc"],"dasblog_compressedtitle":["More+Architect+Bloggers"],"dasblog_compressedtitleunique":["2004\/11\/11\/More+Architect+Bloggers"]}},"previous_url":"http:\/\/devhawk.net\/2004\/11\/10\/halo-2-stats\/","next_url":"http:\/\/devhawk.net\/2004\/11\/15\/blog-rolls\/"}