{
  "slug": "agdlr-0-5",
  "title": "AgDLR 0.5",
  "date": "2009-03-24T23:25:42-07:00",
  "modified": "2011-04-17T01:09:56-07:00",
  "csv-category-slugs": "IronPython|ironpython",
  "csv-tag-slugs": "DLR|dlr,Silverlight|silverlight",
  "author": "DevHawk|devhawk|harry@devhawk.net",
  "comment-count": 2,
  "dasblog-entry-id": "cbfe07b7-55ff-497a-9edb-154fd819e1ed",
  "dasblog-title": "AgDLR+05",
  "dasblog-unique-title": "2009/03/25/AgDLR+05",
  "sha1": "dc13654ace4e968595b558bc346ea5bafe87b3cf"
}