[
  {
    "author-name": "Matt Berther",
    "author-email": "matt@mattberther.com",
    "author-url": "http://www.mattberther.com",
    "date": "2004-01-09T20:52:04-08:00",
    "content": "So, pardon my ignorance...\n\nIs there a way to get integrated POP3 email from MSN9 on a computer that doesnt have MSN9 on it?\n\nie: can I go to some website and check email when Im away from this computer and get it all in one spot?"
  },
  {
    "author-name": "Harry",
    "author-email": "",
    "author-url": "",
    "date": "2004-01-10T22:54:29-08:00",
    "content": "As far as I understand (i.e. I'm not on the MSN team, so I'm not the expert), the POP3 support is a feature of the MSN client."
  }
]